reconframe/Commands.py
reconframe/Helpers.py
reconframe/Intel.py
reconframe/Strategy.py
reconframe/__init__.py
reconframe-0.1.0.dist-info/LICENSE
reconframe-0.1.0.dist-info/METADATA
reconframe-0.1.0.dist-info/WHEEL
reconframe-0.1.0.dist-info/entry_points.txt
reconframe-0.1.0.dist-info/top_level.txt
reconframe-0.1.0.dist-info/RECORD
