Metadata-Version: 2.1
Name: reconframe
Version: 0.1.0
Summary: A Reconnaissance Framework for Penetration Testing
Home-page: https://github.com/0xcrypto/reconframe
Author: 0xcrypto
Author-email: me@ivxenog.in
License: UNKNOWN
Platform: UNKNOWN
Classifier: Programming Language :: Python :: 3
Classifier: License :: OSI Approved :: MIT License
Classifier: Operating System :: OS Independent
Requires-Python: >=3.6
